[
  {
    "id": "_meta",
    "name": "大师夜",
    "author": "王基"
  },
  {
    "id": "washerwoman"
  },
  {
    "id": "librarian"
  },
  {
    "id": "investigator"
  },
  {
    "id": "chef"
  },
  {
    "id": "empath"
  },
  {
    "id": "fortune_teller"
  },
  {
    "id": "undertaker"
  },
  {
    "id": "monk"
  },
  {
    "id": "ravenkeeper"
  },
  {
    "id": "virgin"
  },
  {
    "id": "slayer"
  },
  {
    "id": "soldier"
  },
  {
    "id": "mayor"
  },
  {
    "id": "butler"
  },
  {
    "id": "drunk"
  },
  {
    "id": "recluse"
  },
  {
    "id": "saint"
  },
  {
    "id": "poisoner"
  },
  {
    "id": "spy"
  },
  {
    "id": "scarlet_woman"
  },
  {
    "id": "baron"
  },
  {
    "id": "imp"
  },
  {
    "id": "custom_traveler_1",
    "image": "https://oss.gstonegames.com/data_file/clocktower/role_icon/custom/d_1234680695861_1a8706ca.jpg",
    "edition": "custom",
    "name": "舞龙身",
    "ability": "你无法被流放。每个白天舞龙头可以向一名非旅行者玩家发起流放，此次流放仅舞龙能参与且半数以上舞龙同意即可流放成功。[不可选择]",
    "team": "traveler",
    "firstNight": 0,
    "otherNight": 0,
    "firstNightReminder": "",
    "otherNightReminder": "",
    "reminders": [],
    "setup": 0
  },
  {
    "id": "special_rule_basic",
    "team": "special_rule",
    "title": "基础规则",
    "rules": [
      {
        "title": "可能",
        "content": "某些事情“可能”发生。代表由说书人来决定该事情是否发生。"
      },
      {
        "title": "中毒",
        "content": "中毒的玩家会失去能力，但会认为自己仍具有能力，说书人会做出这些玩家仍然具有能力的行为。如果中毒玩家的角色能力会给他提供信息，说书人可能会给出错误信息，中毒的玩家不会得知自己中毒。"
      }
    ]
  },
  {
    "id": "special_rule_madness",
    "team": "special_rule",
    "title": "疯狂",
    "content": "你需要\"疯狂\"地证明自己是某个角色或阵营，或者证明某位玩家是某个角色或阵营。如果你没有\"疯狂\"证明，你可能会被处决。"
  },
  {
    "id": "custom_legend_shop",
    "image": "https://oss.gstonegames.com/data_file/clocktower/web/icons/spirit_of_ivory.png",
    "edition": "custom",
    "name": "神秘商人",
    "ability": "这是一个自定义的未知团队角色示例。可以用于展示任何未知team类型。默认使用翠墨绿色。",
    "team": "legend_shops",
    "firstNight": 0,
    "otherNight": 0,
    "reminders": []
  },
  {
    "id": "custom_neutral_role",
    "image": "https://oss.gstonegames.com/data_file/clocktower/web/icons/hells_librarian.png",
    "edition": "custom",
    "name": "中立角色",
    "ability": "这个角色使用自定义颜色。可以在JSON中通过teamColor字段指定颜色。",
    "team": "neutral",
    "teamColor": "#8b7355",
    "firstNight": 0,
    "otherNight": 0,
    "reminders": []
  }
]